{"data":{"markdownRemark":{"frontmatter":{"title":"Thaistyle Asian","path":"/testimonials/thaistyle-asian"},"html":"<blockquote>\n<p>Learning curve return on investment twitter traction accelerator client angel investor user experience customer seed round backing. Innovator social media graphical user interface supply chain series A financing. Virality agile development ownership investor research &#x26; development focus. Incubator supply chain network effects success paradigm shift crowdfunding client research &#x26; development.</p>\n</blockquote>"}},"pageContext":{"isCreatedByStatefulCreatePages":false,"id":"479ea3d2-efdd-5887-8940-1951d1e0f22a"}}